Workbook
Name Slicer_Category: #N/A
Name Slicer_Quarter: #N/A
Name Slicer_Region: #N/A
Name Slicer_Year: #N/A

Sheet Supermart Grocery Sales - Retai
A1: Order ID | B1: Customer Name | C1: Category | D1: Sub Category | E1: City | F1: Order Date | G1: Region | H1: Sales | I1: Discount | J1: Profit | K1: State
A2: OD1 | B2: Harish | C2: Oil & Masala | D2: Masalas | E2: Vellore | F2: 43047 | G2: North | H2: 1254 | I2: 0.12 | J2: 401.28 | K2: Tamil Nadu
A3: OD2 | B3: Sudha | C3: Beverages | D3: Health Drinks | E3: Krishnagiri | F3: 43047 | G3: South | H3: 749 | I3: 0.18 | J3: 149.8 | K3: Tamil Nadu
A4: OD3 | B4: Hussain | C4: Food Grains | D4: Atta & Flour | E4: Perambalur | F4: 42898 | G4: West | H4: 2360 | I4: 0.21 | J4: 165.2 | K4: Tamil Nadu
A5: OD4 | B5: Jackson | C5: Fruits & Veggies | D5: Fresh Vegetables | E5: Dharmapuri | F5: 42654 | G5: South | H5: 896 | I5: 0.25 | J5: 89.6 | K5: Tamil Nadu
A6: OD5 | B6: Ridhesh | C6: Food Grains | D6: Organic Staples | E6: Ooty | F6: 42654 | G6: South | H6: 2355 | I6: 0.26 | J6: 918.45 | K6: Tamil Nadu
A7: OD6 | B7: Adavan | C7: Food Grains | D7: Organic Staples | E7: Dharmapuri | F7: 42164 | G7: West | H7: 2305 | I7: 0.26 | J7: 322.7 | K7: Tamil Nadu
A8: OD7 | B8: Jonas | C8: Fruits & Veggies | D8: Fresh Vegetables | E8: Trichy | F8: 42164 | G8: West | H8: 826 | I8: 0.33 | J8: 346.92 | K8: Tamil Nadu
A9: OD8 | B9: Hafiz | C9: Fruits & Veggies | D9: Fresh Fruits | E9: Ramanadhapuram | F9: 42164 | G9: West | H9: 1847 | I9: 0.32 | J9: 147.76 | K9: Tamil Nadu
A10: OD9 | B10: Hafiz | C10: Bakery | D10: Biscuits | E10: Tirunelveli | F10: 42164 | G10: West | H10: 791 | I10: 0.23 | J10: 181.93 | K10: Tamil Nadu
A11: OD10 | B11: Krithika | C11: Bakery | D11: Cakes | E11: Chennai | F11: 42164 | G11: West | H11: 1795 | I11: 0.27 | J11: 484.65 | K11: Tamil Nadu
A12: OD11 | B12: Ganesh | C12: Snacks | D12: Chocolates | E12: Karur | F12: 42164 | G12: West | H12: 1903 | I12: 0.13 | J12: 437.69 | K12: Tamil Nadu
A13: OD12 | B13: Yadav | C13: Eggs, Meat & Fish | D13: Eggs | E13: Namakkal | F13: 42164 | G13: West | H13: 701 | I13: 0.1 | J13: 308.44 | K13: Tamil Nadu
... A9995: OD9994 | B9995: Ganesh | C9995: Food Grains | D9995: Atta & Flour | E9995: Tirunelveli | F9995: 43207 | G9995: West | H9995: 1034 | I9995: 0.28 | J9995: 165.44 | K9995: Tamil Nadu

Sheet Data Model
A1: Year | B1: Month | C1: Month_Name | D1: Quarter | E1: Profit_Margin | F1: Sales | G1: Profit | H1: Category | I1: Sub Category | J1: Region | K1: Customer Name
A2: =YEAR('Supermart Grocery Sales - Retai'!F:F) -> 2017 | B2: =MONTH('Supermart Grocery Sales - Retai'!F:F) -> 11 | C2: {=CHOOSE(_xlfn.ANCHORARRAY(B2), "Jan", "Feb", "Mar", "Apr", "May", "Jun", "Jul", "Aug", "Sep", "Oct", "Nov", "Dec")} -> Nov | D2: ="Q"&ROUNDUP(MONTH('Supermart Grocery Sales - Retai'!F2)/3,0) -> Q4 | E2: =tbl_DataModel[[#This Row],[Profit]]/tbl_DataModel[[#This Row],[Sales]] -> 0.32 | F2: 1254 | G2: 401.28 | H2: Oil & Masala | I2: Masalas | J2: North | K2: Harish
A3: =YEAR('Supermart Grocery Sales - Retai'!F:F) -> 2017 | B3: =MONTH('Supermart Grocery Sales - Retai'!F:F) -> 11 | C3: {=CHOOSE(_xlfn.ANCHORARRAY(B3), "Jan", "Feb", "Mar", "Apr", "May", "Jun", "Jul", "Aug", "Sep", "Oct", "Nov", "Dec")} -> Nov | D3: ="Q"&ROUNDUP(MONTH('Supermart Grocery Sales - Retai'!F3)/3,0) -> Q4 | E3: =tbl_DataModel[[#This Row],[Profit]]/tbl_DataModel[[#This Row],[Sales]] -> 0.2 | F3: 749 | G3: 149.8 | H3: Beverages | I3: Health Drinks | J3: South | K3: Sudha
A4: =YEAR('Supermart Grocery Sales - Retai'!F:F) -> 2017 | B4: =MONTH('Supermart Grocery Sales - Retai'!F:F) -> 6 | C4: {=CHOOSE(_xlfn.ANCHORARRAY(B4), "Jan", "Feb", "Mar", "Apr", "May", "Jun", "Jul", "Aug", "Sep", "Oct", "Nov", "Dec")} -> Jun | D4: ="Q"&ROUNDUP(MONTH('Supermart Grocery Sales - Retai'!F4)/3,0) -> Q2 | E4: =tbl_DataModel[[#This Row],[Profit]]/tbl_DataModel[[#This Row],[Sales]] -> 0.07 | F4: 2360 | G4: 165.2 | H4: Food Grains | I4: Atta & Flour | J4: West | K4: Hussain
A5: =YEAR('Supermart Grocery Sales - Retai'!F:F) -> 2016 | B5: =MONTH('Supermart Grocery Sales - Retai'!F:F) -> 10 | C5: {=CHOOSE(_xlfn.ANCHORARRAY(B5), "Jan", "Feb", "Mar", "Apr", "May", "Jun", "Jul", "Aug", "Sep", "Oct", "Nov", "Dec")} -> Oct | D5: ="Q"&ROUNDUP(MONTH('Supermart Grocery Sales - Retai'!F5)/3,0) -> Q4 | E5: =tbl_DataModel[[#This Row],[Profit]]/tbl_DataModel[[#This Row],[Sales]] -> 0.1 | F5: 896 | G5: 89.6 | H5: Fruits & Veggies | I5: Fresh Vegetables | J5: South | K5: Jackson
A6: =YEAR('Supermart Grocery Sales - Retai'!F:F) -> 2016 | B6: =MONTH('Supermart Grocery Sales - Retai'!F:F) -> 10 | C6: {=CHOOSE(_xlfn.ANCHORARRAY(B6), "Jan", "Feb", "Mar", "Apr", "May", "Jun", "Jul", "Aug", "Sep", "Oct", "Nov", "Dec")} -> Oct | D6: ="Q"&ROUNDUP(MONTH('Supermart Grocery Sales - Retai'!F6)/3,0) -> Q4 | E6: =tbl_DataModel[[#This Row],[Profit]]/tbl_DataModel[[#This Row],[Sales]] -> 0.39 | F6: 2355 | G6: 918.45 | H6: Food Grains | I6: Organic Staples | J6: South | K6: Ridhesh
A7: =YEAR('Supermart Grocery Sales - Retai'!F:F) -> 2015 | B7: =MONTH('Supermart Grocery Sales - Retai'!F:F) -> 6 | C7: {=CHOOSE(_xlfn.ANCHORARRAY(B7), "Jan", "Feb", "Mar", "Apr", "May", "Jun", "Jul", "Aug", "Sep", "Oct", "Nov", "Dec")} -> Jun | D7: ="Q"&ROUNDUP(MONTH('Supermart Grocery Sales - Retai'!F7)/3,0) -> Q2 | E7: =tbl_DataModel[[#This Row],[Profit]]/tbl_DataModel[[#This Row],[Sales]] -> 0.14 | F7: 2305 | G7: 322.7 | H7: Food Grains | I7: Organic Staples | J7: West | K7: Adavan
A8: =YEAR('Supermart Grocery Sales - Retai'!F:F) -> 2015 | B8: =MONTH('Supermart Grocery Sales - Retai'!F:F) -> 6 | C8: {=CHOOSE(_xlfn.ANCHORARRAY(B8), "Jan", "Feb", "Mar", "Apr", "May", "Jun", "Jul", "Aug", "Sep", "Oct", "Nov", "Dec")} -> Jun | D8: ="Q"&ROUNDUP(MONTH('Supermart Grocery Sales - Retai'!F8)/3,0) -> Q2 | E8: =tbl_DataModel[[#This Row],[Profit]]/tbl_DataModel[[#This Row],[Sales]] -> 0.42 | F8: 826 | G8: 346.92 | H8: Fruits & Veggies | I8: Fresh Vegetables | J8: West | K8: Jonas
A9: =YEAR('Supermart Grocery Sales - Retai'!F:F) -> 2015 | B9: =MONTH('Supermart Grocery Sales - Retai'!F:F) -> 6 | C9: {=CHOOSE(_xlfn.ANCHORARRAY(B9), "Jan", "Feb", "Mar", "Apr", "May", "Jun", "Jul", "Aug", "Sep", "Oct", "Nov", "Dec")} -> Jun | D9: ="Q"&ROUNDUP(MONTH('Supermart Grocery Sales - Retai'!F9)/3,0) -> Q2 | E9: =tbl_DataModel[[#This Row],[Profit]]/tbl_DataModel[[#This Row],[Sales]] -> 0.08 | F9: 1847 | G9: 147.76 | H9: Fruits & Veggies | I9: Fresh Fruits | J9: West | K9: Hafiz
A10: =YEAR('Supermart Grocery Sales - Retai'!F:F) -> 2015 | B10: =MONTH('Supermart Grocery Sales - Retai'!F:F) -> 6 | C10: {=CHOOSE(_xlfn.ANCHORARRAY(B10), "Jan", "Feb", "Mar", "Apr", "May", "Jun", "Jul", "Aug", "Sep", "Oct", "Nov", "Dec")} -> Jun | D10: ="Q"&ROUNDUP(MONTH('Supermart Grocery Sales - Retai'!F10)/3,0) -> Q2 | E10: =tbl_DataModel[[#This Row],[Profit]]/tbl_DataModel[[#This Row],[Sales]] -> 0.23 | F10: 791 | G10: 181.93 | H10: Bakery | I10: Biscuits | J10: West | K10: Hafiz
A11: =YEAR('Supermart Grocery Sales - Retai'!F:F) -> 2015 | B11: =MONTH('Supermart Grocery Sales - Retai'!F:F) -> 6 | C11: {=CHOOSE(_xlfn.ANCHORARRAY(B11), "Jan", "Feb", "Mar", "Apr", "May", "Jun", "Jul", "Aug", "Sep", "Oct", "Nov", "Dec")} -> Jun | D11: ="Q"&ROUNDUP(MONTH('Supermart Grocery Sales - Retai'!F11)/3,0) -> Q2 | E11: =tbl_DataModel[[#This Row],[Profit]]/tbl_DataModel[[#This Row],[Sales]] -> 0.27 | F11: 1795 | G11: 484.65 | H11: Bakery | I11: Cakes | J11: West | K11: Krithika
A12: =YEAR('Supermart Grocery Sales - Retai'!F:F) -> 2015 | B12: =MONTH('Supermart Grocery Sales - Retai'!F:F) -> 6 | C12: {=CHOOSE(_xlfn.ANCHORARRAY(B12), "Jan", "Feb", "Mar", "Apr", "May", "Jun", "Jul", "Aug", "Sep", "Oct", "Nov", "Dec")} -> Jun | D12: ="Q"&ROUNDUP(MONTH('Supermart Grocery Sales - Retai'!F12)/3,0) -> Q2 | E12: =tbl_DataModel[[#This Row],[Profit]]/tbl_DataModel[[#This Row],[Sales]] -> 0.23 | F12: 1903 | G12: 437.69 | H12: Snacks | I12: Chocolates | J12: West | K12: Ganesh
A13: =YEAR('Supermart Grocery Sales - Retai'!F:F) -> 2015 | B13: =MONTH('Supermart Grocery Sales - Retai'!F:F) -> 6 | C13: {=CHOOSE(_xlfn.ANCHORARRAY(B13), "Jan", "Feb", "Mar", "Apr", "May", "Jun", "Jul", "Aug", "Sep", "Oct", "Nov", "Dec")} -> Jun | D13: ="Q"&ROUNDUP(MONTH('Supermart Grocery Sales - Retai'!F13)/3,0) -> Q2 | E13: =tbl_DataModel[[#This Row],[Profit]]/tbl_DataModel[[#This Row],[Sales]] -> 0.44 | F13: 701 | G13: 308.44 | H13: Eggs, Meat & Fish | I13: Eggs | J13: West | K13: Yadav
... A9995: =YEAR('Supermart Grocery Sales - Retai'!F:F) -> 2018 | B9995: =MONTH('Supermart Grocery Sales - Retai'!F:F) -> 4 | C9995: {=CHOOSE(_xlfn.ANCHORARRAY(B9995), "Jan", "Feb", "Mar", "Apr", "May", "Jun", "Jul", "Aug", "Sep", "Oct", "Nov", "Dec")} -> Apr | D9995: ="Q"&ROUNDUP(MONTH('Supermart Grocery Sales - Retai'!F9995)/3,0) -> Q2 | E9995: =tbl_DataModel[[#This Row],[Profit]]/tbl_DataModel[[#This Row],[Sales]] -> 0.16 | F9995: 1034 | G9995: 165.44 | H9995: Food Grains | I9995: Atta & Flour | J9995: West | K9995: Ganesh

Sheet Pivot_Tables
A1: Sum of Sales | C1: Sum of Profit | E1: Row Labels | F1: Sum of Sales | H1: Row Labels | I1: Sum of Sales
A2: 14956982 | C2: 3747121.2 | E2: Jan | F2: 577972 | H2: Bakery | I2: 2112281
E3: Feb | F3: 456102 | H3: Beverages | I3: 2085313
E4: Mar | F4: 1053980 | H4: Eggs, Meat & Fish | I4: 2267401
E5: Apr | F5: 998453 | H5: Food Grains | I5: 2115272
A6: Row Labels | B6: Sum of Sales | E6: May | F6: 1086920 | H6: Fruits & Veggies | I6: 2100727
A7: Rice | B7: 498323 | E7: Jun | F7: 1057808 | H7: Oil & Masala | I7: 2038442
A8: Organic Fruits | B8: 503402 | E8: Jul | F8: 1089385 | H8: Snacks | I8: 2237546
A9: Organic Vegetables | B9: 520271 | E9: Aug | F9: 1046807 | H9: Grand Total | I9: 14956982
A10: Chicken | B10: 520497 | E10: Sep | F10: 2064266
A11: Dals & Pulses | B11: 523371 | E11: Oct | F11: 1243289
A12: Fresh Vegetables | B12: 525842 | E12: Nov | F12: 2193924 | H12: Row Labels | I12: Sum of Sales
A13: Atta & Flour | B13: 534649 | E13: Dec | F13: 2088076 | H13: Central | I13: 3468156
A14: Fresh Fruits | B14: 551212 | E14: Grand Total | F14: 14956982 | H14: East | I14: 4248368
A15: Organic Staples | B15: 558929 | H15: North | I15: 1254
A16: Fish | B16: 560548 | H16: South | I16: 2440461
A17: Eggs | B17: 575156 | H17: West | I17: 4798743
A18: Mutton | B18: 611200 | E18: Row Labels | F18: Sum of Sales | H18: Grand Total | I18: 14956982
A19: Edible Oil & Ghee | B19: 668086 | E19: Arutra | F19: 325720
A20: Spices | B20: 672876 | E20: Krithika | F20: 334361
A21: Biscuits | B21: 684083 | E21: Amrish | F21: 333351 | H21: Row Labels | I21: YoY Growth %
A22: Cakes | B22: 685612 | E22: Verma | F22: 331665 | H22: 2015
A23: Masalas | B23: 697480 | E23: Vidya | F23: 321798 | H23: 2016 | I23: 0.052547403
A24: Chocolates | B24: 733898 | E24: Grand Total | F24: 1646895 | H24: 2017 | I24: 0.23625884
A25: Noodles | B25: 735435 | H25: 2018 | I25: 0.28554368
A26: Breads & Buns | B26: 742586 | H26: Grand Total
A27: Cookies | B27: 768213
A28: Soft Drinks | B28: 1033874
A29: Health Drinks | B29: 1051439
A30: Grand Total | B30: 14956982

Sheet Dashboard
C6: Total Sales | E6: Total Profit | G6: Total Profit Margin (%)
C7: =GETPIVOTDATA("Sales",Pivot_Tables!$A$1) -> 14956982 | E7: =GETPIVOTDATA("Profit",Pivot_Tables!$C$1) -> 3747121.2 | G7: =E7/C7 -> 0.25052656
